configu/__init__.py
configu/commands/__init__.py
configu/commands/eval_command.py
configu/commands/export_command.py
configu/commands/upsert_command.py
configu/core/__init__.py
configu/core/command.py
configu/core/config_schema.py
configu/core/config_set.py
configu/core/config_store.py
configu/core/generated.py
configu/stores/__init__.py
configu/stores/aws_secrets_manager_store.py
configu/stores/azure_key_vault_store.py
configu/stores/configu_store.py
configu/stores/gcp_secret_manager.py
configu/stores/hashicorp_vault_store.py
configu/stores/in_memory_store.py
configu/stores/json_file_store.py
configu/stores/key_value_store.py
configu/stores/kubernetes_secret_store.py
configu/utils.py
configu-0.6.3.dist-info/METADATA
configu-0.6.3.dist-info/WHEEL
configu-0.6.3.dist-info/RECORD
