Metadata-Version: 2.1
Name: configu
Version: 0.6.3
Summary: Configu Python SDK
Home-page: https://configu.com/
License: Apache-2.0
Keywords: cfgu,configu,configu-sdk,configu-python-sdk
Author: Configu
Author-email: info@configu.com
Maintainer: Ron Roditi
Maintainer-email: ron@configu.com
Requires-Python: >=3.9,<3.12
Classifier: Development Status :: 5 - Production/Stable
Classifier: Intended Audience :: Developers
Classifier: License :: OSI Approved :: Apache Software License
Classifier: Operating System :: OS Independent
Classifier: Programming Language :: Python :: 3
Classifier: Programming Language :: Python :: 3.9
Classifier: Programming Language :: Python :: 3.10
Classifier: Programming Language :: Python :: 3.11
Classifier: Programming Language :: Python :: 3 :: Only
Classifier: Topic :: Software Development
Requires-Dist: azure-identity (>=1.13.0,<2.0.0)
Requires-Dist: azure-keyvault-secrets (>=4.7.0,<5.0.0)
Requires-Dist: boto3 (>=1.26.155,<2.0.0)
Requires-Dist: boto3-stubs[secretsmanager] (>=1.26.155,<2.0.0)
Requires-Dist: chevron (>=0.14.0,<0.15.0)
Requires-Dist: google-cloud-secret-manager (>=2.16.1,<3.0.0)
Requires-Dist: jsonschema (>=4.20.0,<5.0.0)
Requires-Dist: kubernetes (>=26.1.0,<27.0.0)
Requires-Dist: py-validator (>=0.18.0,<0.19.0)
Requires-Dist: requests (>=2.28.1,<3.0.0)
Project-URL: Documentation, https://configu.com/docs/
Project-URL: Repository, https://github.com/configu/configu
